disk_monitor/__init__.py
disk_monitor/main.py
disk_monitor-0.1.1.dist-info/LICENSE
disk_monitor-0.1.1.dist-info/METADATA
disk_monitor-0.1.1.dist-info/WHEEL
disk_monitor-0.1.1.dist-info/entry_points.txt
disk_monitor-0.1.1.dist-info/top_level.txt
disk_monitor-0.1.1.dist-info/RECORD
