Metadata-Version: 2.1
Name: disk-monitor
Version: 0.1.1
Summary: A disk hex data monitor
Home-page: https://github.com/zyx1121/disk-monitor
Author: Loki
Author-email: yongxiang.zhan@outlook.com
Classifier: License :: OSI Approved :: MIT License
Classifier: Programming Language :: Python :: 3
Classifier: Operating System :: OS Independent
Requires-Python: >=3.6
License-File: LICENSE
Requires-Dist: rich
